paquete/__init__.py
paquete/saludos_esto_a_ignorar.py
paquete/adios/__init__.py
paquete/adios/despedidas.py
paquete/hola/__init__.py
paquete/hola/saludos.py
tests/__init__.py
tests/test_hola.py
paquete_diegogabyolmos-0.6.dist-info/LICENSE
paquete_diegogabyolmos-0.6.dist-info/METADATA
paquete_diegogabyolmos-0.6.dist-info/WHEEL
paquete_diegogabyolmos-0.6.dist-info/top_level.txt
paquete_diegogabyolmos-0.6.dist-info/RECORD
